README.md
setup.cfg
setup.py
nogui/__init__.py
nogui/forms.py
nogui.egg-info/PKG-INFO
nogui.egg-info/SOURCES.txt
nogui.egg-info/dependency_links.txt
nogui.egg-info/top_level.txt