Metadata-Version: 1.1
Name: nogui
Version: 0.0.1
Summary: A simple set of functions to communicate with the users via terminal rather than gui.
Home-page: https://github.com/MatteoLacki/nogui.git
Author: MatteoLacki
Author-email: matteo.lacki@gmail.com
License: UNKNOWN
Keywords: terminal gui,cli forms
Platform: UNKNOWN
Classifier: Development Status :: 1 - Planning
Classifier: Programming Language :: Python :: 3.6
Classifier: Programming Language :: Python :: 3.7
